abcde-1.0.0.dev1.dist-info/DESCRIPTION.rst
abcde-1.0.0.dev1.dist-info/METADATA
abcde-1.0.0.dev1.dist-info/RECORD
abcde-1.0.0.dev1.dist-info/WHEEL
abcde-1.0.0.dev1.dist-info/metadata.json
abcde-1.0.0.dev1.dist-info/top_level.txt
mm/__init__.py
mm/classOne.py
mm/classTwo.py
