Metadata-Version: 2.0
Name: abcde
Version: 1.0.0.dev1
Summary: A yaoj client python project
Home-page: https://github.com/yaoj/yao-py
Author: yaoj
Author-email: y_jian_17@126.com
License: MIT
Keywords: yaoj client python
Platform: UNKNOWN
Classifier: Development Status :: 4 - Beta
Classifier: Intended Audience :: Developers
Classifier: Topic :: Software Development :: Build Tools
Classifier: License :: OSI Approved :: MIT License
Classifier: Programming Language :: Python :: 2.6
Classifier: Programming Language :: Python :: 2.7
Classifier: Programming Language :: Python :: 3
Classifier: Programming Language :: Python :: 3.3
Classifier: Programming Language :: Python :: 3.4
Classifier: Programming Language :: Python :: 3.5
